pytdm/__init__.py
pytdm/mowa.py
pytdm/nums.py
pytdm/translacja.py
pytdm-0.1.2.dist-info/LICENSE
pytdm-0.1.2.dist-info/METADATA
pytdm-0.1.2.dist-info/WHEEL
pytdm-0.1.2.dist-info/top_level.txt
pytdm-0.1.2.dist-info/RECORD
