Metadata-Version: 2.1
Name: pytdm
Version: 0.1.2
Summary: Pytońska treść do mowy – Polish Text to Speech library for Python
Home-page: https://github.com/test0wanie/PyTDM
Author: test0wanie
Author-email: test0wanie@protonmail.com
License: MIT
Platform: UNKNOWN
Classifier: Programming Language :: Python :: 3
Classifier: License :: OSI Approved :: MIT License
Classifier: Operating System :: OS Independent
Classifier: Development Status :: 3 - Alpha
Requires-Python: >=3.6
Requires-Dist: pyttsx3 (>=2.7)
